odoo/addons/ai_oca_bridge_helpdesk_mgmt/README.rst
odoo/addons/ai_oca_bridge_helpdesk_mgmt/__init__.py
odoo/addons/ai_oca_bridge_helpdesk_mgmt/__manifest__.py
odoo/addons/ai_oca_bridge_helpdesk_mgmt/i18n/ai_oca_bridge_helpdesk_mgmt.pot
odoo/addons/ai_oca_bridge_helpdesk_mgmt/i18n/es.po
odoo/addons/ai_oca_bridge_helpdesk_mgmt/i18n/es_VE.po
odoo/addons/ai_oca_bridge_helpdesk_mgmt/i18n/it.po
odoo/addons/ai_oca_bridge_helpdesk_mgmt/i18n/pt_BR.po
odoo/addons/ai_oca_bridge_helpdesk_mgmt/models/__init__.py
odoo/addons/ai_oca_bridge_helpdesk_mgmt/models/helpdesk_ticket.py
odoo/addons/ai_oca_bridge_helpdesk_mgmt/readme/CONTRIBUTORS.md
odoo/addons/ai_oca_bridge_helpdesk_mgmt/readme/DESCRIPTION.md
odoo/addons/ai_oca_bridge_helpdesk_mgmt/static/description/icon.png
odoo/addons/ai_oca_bridge_helpdesk_mgmt/static/description/icon.svg
odoo/addons/ai_oca_bridge_helpdesk_mgmt/static/description/index.html
odoo_addon_ai_oca_bridge_helpdesk_mgmt-16.0.1.0.0.10.dist-info/METADATA
odoo_addon_ai_oca_bridge_helpdesk_mgmt-16.0.1.0.0.10.dist-info/WHEEL
odoo_addon_ai_oca_bridge_helpdesk_mgmt-16.0.1.0.0.10.dist-info/top_level.txt
odoo_addon_ai_oca_bridge_helpdesk_mgmt-16.0.1.0.0.10.dist-info/RECORD
