Metadata-Version: 2.1
Name: odoo-addon-ai_oca_bridge_helpdesk_mgmt
Version: 16.0.1.0.0.10
Summary: Integrate AI Bridge with Helpdesk Management
Home-page: https://github.com/OCA/ai
Author: Dixmit,Odoo Community Association (OCA)
Author-email: support@odoo-community.org
License: AGPL-3
Classifier: Programming Language :: Python
Classifier: Framework :: Odoo
Classifier: Framework :: Odoo :: 16.0
Classifier: License :: OSI Approved :: GNU Affero General Public License v3
Requires-Python: >=3.10
Requires-Dist: odoo-addon-ai-oca-bridge<16.1dev,>=16.0dev
Requires-Dist: odoo-addon-helpdesk-mgmt<16.1dev,>=16.0dev
Requires-Dist: odoo<16.1dev,>=16.0a
